pytest_codeblocks/__about__.py
pytest_codeblocks/__init__.py
pytest_codeblocks/main.py
pytest_codeblocks/plugin.py
pytest_codeblocks-0.16.2.dist-info/entry_points.txt
pytest_codeblocks-0.16.2.dist-info/LICENSE.txt
pytest_codeblocks-0.16.2.dist-info/WHEEL
pytest_codeblocks-0.16.2.dist-info/METADATA
pytest_codeblocks-0.16.2.dist-info/RECORD
