Metadata-Version: 2.1
Name: pytest_codeblocks
Version: 0.16.2
Summary: Test code blocks in your READMEs
Author-email: Nico Schlömer <nico.schloemer@gmail.com>
Requires-Python: >=3.7
Classifier: Development Status :: 5 - Production/Stable
Classifier: Framework :: Pytest
Classifier: Intended Audience :: Developers
Classifier: License :: OSI Approved :: MIT License
Classifier: Operating System :: OS Independent
Classifier: Programming Language :: Python
Classifier: Programming Language :: Python :: 3
Classifier: Programming Language :: Python :: 3.7
Classifier: Programming Language :: Python :: 3.8
Classifier: Programming Language :: Python :: 3.9
Classifier: Programming Language :: Python :: 3.10
Classifier: Programming Language :: Python :: 3.11
Classifier: Programming Language :: Python :: 3.12
Requires-Dist: pytest >= 7.0.0
Project-URL: Code, https://github.com/nschloe/pytest-codeblocks
Project-URL: Funding, https://github.com/sponsors/nschloe
Project-URL: Homepage, https://github.com/nschloe/pytest-codeblocks
Project-URL: Issues, https://github.com/nschloe/pytest-codeblocks/issues
